{
  "time": 1660549052.0,
  "market": {
    "Apple": {
      "ask": 22.0,
      "bid": 6.0
    },
    "Apple Gummy": {
      "ask": 112.0,
      "bid": 52.0
    },
    "Apple Yogurt": {
      "ask": 1000000000000.0,
      "bid": 50.0
    },
    "Aqua Essence": {
      "ask": 58.0,
      "bid": 29.0
    },
    "Arabica Coffee Bean": {
      "ask": 125.0,
      "bid": 73.0
    },
    "Artisan Tea": {
      "ask": 840.0,
      "bid": 569.0
    },
    "Attack Coffee": {
      "ask": 320.0,
      "bid": 150.0
    },
    "Azure Boots": {
      "ask": 7457.0,
      "bid": -1.0
    },
    "Azure Brush": {
      "ask": 9977.0,
      "bid": 1150.0
    },
    "Azure Buckler": {
      "ask": 13000.0,
      "bid": 1566.0
    },
    "Azure Bulwark": {
      "ask": 11000.0,
      "bid": 2300.0
    },
    "Azure Cheese": {
      "ask": 195.0,
      "bid": 121.0
    },
    "Azure Enhancer": {
      "ask": 16599.0,
      "bid": 1625.0
    },
    "Azure Gauntlets": {
      "ask": -1.0,
      "bid": 3601.0
    },
    "Azure Hammer": {
      "ask": 13300.0,
      "bid": 1435.0
    },
    "Azure Helmet": {
      "ask": -1.0,
      "bid": 3600.0
    },
    "Azure Mace": {
      "ask": -1.0,
      "bid": 3342.0
    },
    "Azure Milk": {
      "ask": 42.0,
      "bid": 29.0
    },
    "Azure Plate Body": {
      "ask": 19999.0,
      "bid": 2050.0
    },
    "Azure Plate Legs": {
      "ask": 50000.0,
      "bid": 5000.0
    },
    "Azure Pot": {
      "ask": 12886.0,
      "bid": 1150.0
    },
    "Azure Shears": {
      "ask": 7355.0,
      "bid": 1304.0
    },
    "Azure Spatula": {
      "ask": 11083.0,
      "bid": 1150.0
    },
    "Azure Spear": {
      "ask": 15110.0,
      "bid": 3020.0
    },
    "Azure Sword": {
      "ask": 9025.0,
      "bid": 1875.0
    },
    "Bear Essence": {
      "ask": 74.0,
      "bid": 61.0
    },
    "Berserk": {
      "ask": 234410.0,
      "bid": 140010.0
    },
    "Black Bear Fluff": {
      "ask": 64410.0,
      "bid": 23000.0
    },
    "Black Bear Shoes": {
      "ask": 724866.0,
      "bid": 1.0
    },
    "Black Tea Leaf": {
      "ask": 69.0,
      "bid": 40.0
    },
    "Blackberry": {
      "ask": 16.0,
      "bid": 12.0
    },
    "Blackberry Cake": {
      "ask": 1000000000000.0,
      "bid": 21.0
    },
    "Blackberry Donut": {
      "ask": 139.0,
      "bid": -1.0
    },
    "Blessed Tea": {
      "ask": 731.0,
      "bid": 651.0
    },
    "Blueberry": {
      "ask": 16.0,
      "bid": 11.0
    },
    "Blueberry Cake": {
      "ask": 154.0,
      "bid": 22.0
    },
    "Blueberry Donut": {
      "ask": 999999999999.0,
      "bid": 12.0
    },
    "Brewing Tea": {
      "ask": 170.0,
      "bid": 98.0
    },
    "Burble Boots": {
      "ask": 6500.0,
      "bid": 2500.0
    },
    "Burble Brush": {
      "ask": 11605.0,
      "bid": 3895.0
    },
    "Burble Buckler": {
      "ask": 34849.0,
      "bid": -1.0
    },
    "Burble Bulwark": {
      "ask": 25721.0,
      "bid": 8400.0
    },
    "Burble Cheese": {
      "ask": 257.0,
      "bid": 200.0
    },
    "Burble Enhancer": {
      "ask": -1.0,
      "bid": 3007.0
    },
    "Burble Gauntlets": {
      "ask": 17416.0,
      "bid": 4002.0
    },
    "Burble Hammer": {
      "ask": 15000.0,
      "bid": 3054.0
    },
    "Burble Helmet": {
      "ask": 16934.0,
      "bid": -1.0
    },
    "Burble Mace": {
      "ask": 16485.0,
      "bid": -1.0
    },
    "Burble Milk": {
      "ask": 32.0,
      "bid": 31.0
    },
    "Burble Plate Body": {
      "ask": 25000.0,
      "bid": 6000.0
    },
    "Burble Plate Legs": {
      "ask": 19800.0,
      "bid": -1.0
    },
    "Burble Pot": {
      "ask": 39875.0,
      "bid": 5255.0
    },
    "Burble Shears": {
      "ask": 11999.0,
      "bid": 3360.0
    },
    "Burble Spatula": {
      "ask": 9024.0,
      "bid": 3050.0
    },
    "Burble Spear": {
      "ask": 21976.0,
      "bid": 3444.0
    },
    "Burble Sword": {
      "ask": -1.0,
      "bid": 3573.0
    },
    "Burble Tea Leaf": {
      "ask": 235.0,
      "bid": 215.0
    },
    "Cheese": {
      "ask": 128.0,
      "bid": 74.0
    },
    "Cheese Boots": {
      "ask": 550.0,
      "bid": 131.0
    },
    "Cheese Brush": {
      "ask": 9499.0,
      "bid": 171.0
    },
    "Cheese Buckler": {
      "ask": -1.0,
      "bid": 214.0
    },
    "Cheese Bulwark": {
      "ask": 2299.0,
      "bid": 164.0
    },
    "Cheese Enhancer": {
      "ask": 798.0,
      "bid": 302.0
    },
    "Cheese Gauntlets": {
      "ask": -1.0,
      "bid": 173.0
    },
    "Cheese Hammer": {
      "ask": 689.0,
      "bid": 179.0
    },
    "Cheese Helmet": {
      "ask": -1.0,
      "bid": 268.0
    },
    "Cheese Mace": {
      "ask": -1.0,
      "bid": 166.0
    },
    "Cheese Plate Body": {
      "ask": 4218.0,
      "bid": 321.0
    },
    "Cheese Plate Legs": {
      "ask": -1.0,
      "bid": 314.0
    },
    "Cheese Pot": {
      "ask": 666.0,
      "bid": 163.0
    },
    "Cheese Shears": {
      "ask": 714.0,
      "bid": 171.0
    },
    "Cheese Spatula": {
      "ask": 600.0,
      "bid": 168.0
    },
    "Cheese Spear": {
      "ask": -1.0,
      "bid": 171.0
    },
    "Cheese Sword": {
      "ask": 2000.0,
      "bid": 162.0
    },
    "Cheesesmithing Tea": {
      "ask": 447.0,
      "bid": 300.0
    },
    "Cleave": {
      "ask": 69177.0,
      "bid": 50055.0
    },
    "Coin": {
      "ask": -1.0,
      "bid": -1.0
    },
    "Cooking Tea": {
      "ask": 265.0,
      "bid": 150.0
    },
    "Crab Pincer": {
      "ask": 25717.0,
      "bid": 19513.0
    },
    "Crimson Boots": {
      "ask": 22886.0,
      "bid": 5500.0
    },
    "Crimson Brush": {
      "ask": 20271.0,
      "bid": 10000.0
    },
    "Crimson Buckler": {
      "ask": -1.0,
      "bid": 25000.0
    },
    "Crimson Bulwark": {
      "ask": 40000.0,
      "bid": -1.0
    },
    "Crimson Cheese": {
      "ask": 186.5,
      "bid": 153.5
    },
    "Crimson Enhancer": {
      "ask": 25154.0,
      "bid": 10001.0
    },
    "Crimson Gauntlets": {
      "ask": 24995.0,
      "bid": 12000.0
    },
    "Crimson Hammer": {
      "ask": 21796.0,
      "bid": 10000.0
    },
    "Crimson Helmet": {
      "ask": -1.0,
      "bid": 6871.0
    },
    "Crimson Mace": {
      "ask": 32999.0,
      "bid": 10000.0
    },
    "Crimson Milk": {
      "ask": 20.0,
      "bid": 18.0
    },
    "Crimson Plate Body": {
      "ask": 26364.0,
      "bid": -1.0
    },
    "Crimson Plate Legs": {
      "ask": 29999.0,
      "bid": -1.0
    },
    "Crimson Pot": {
      "ask": -1.0,
      "bid": 10001.0
    },
    "Crimson Shears": {
      "ask": -1.0,
      "bid": 10000.0
    },
    "Crimson Spatula": {
      "ask": 21202.0,
      "bid": 10001.0
    },
    "Crimson Spear": {
      "ask": 22804.0,
      "bid": 10000.0
    },
    "Crimson Sword": {
      "ask": 22000.0,
      "bid": 8906.0
    },
    "Cupcake": {
      "ask": 248.0,
      "bid": 15.0
    },
    "Defense Coffee": {
      "ask": 330.0,
      "bid": 200.0
    },
    "Donut": {
      "ask": 99.0,
      "bid": 8.0
    },
    "Dragon Fruit": {
      "ask": 52.0,
      "bid": 37.0
    },
    "Dragon Fruit Gummy": {
      "ask": 396.0,
      "bid": 200.0
    },
    "Dragon Fruit Yogurt": {
      "ask": 284.0,
      "bid": 265.5
    },
    "Efficiency Tea": {
      "ask": 918.0,
      "bid": 739.0
    },
    "Egg": {
      "ask": 17.0,
      "bid": 10.0
    },
    "Emp Tea Leaf": {
      "ask": 274.0,
      "bid": 201.0
    },
    "Enhancing Tea": {
      "ask": 269.0,
      "bid": 20.0
    },
    "Excelsa Coffee Bean": {
      "ask": 98.0,
      "bid": 44.0
    },
    "Eyessence": {
      "ask": 40.0,
      "bid": 38.0
    },
    "Fermenting Tea": {
      "ask": 435.0,
      "bid": 200.0
    },
    "Fieriosa Coffee Bean": {
      "ask": 200.0,
      "bid": 172.0
    },
    "Foraging Tea": {
      "ask": 295.0,
      "bid": 123.0
    },
    "Frenzy": {
      "ask": 129999.0,
      "bid": 100016.0
    },
    "Gathering Tea": {
      "ask": 454.0,
      "bid": 355.0
    },
    "Gator Vest": {
      "ask": 61799.0,
      "bid": 20007.0
    },
    "Giant Pouch": {
      "ask": -1.0,
      "bid": 6000000.0
    },
    "Gobo Essence": {
      "ask": 33.0,
      "bid": 25.0
    },
    "Gobo Slasher": {
      "ask": 23746.0,
      "bid": 20000.0
    },
    "Gobo Smasher": {
      "ask": 36998.0,
      "bid": 20000.0
    },
    "Gobo Stabber": {
      "ask": 21207.0,
      "bid": 10.0
    },
    "Goggles": {
      "ask": 260888.0,
      "bid": 150001.5
    },
    "Gourmet Tea": {
      "ask": 465.0,
      "bid": 300.0
    },
    "Green Tea Leaf": {
      "ask": 109.5,
      "bid": 100.0
    },
    "Grizzly Bear Fluff": {
      "ask": 135319.0,
      "bid": 90301.0
    },
    "Grizzly Bear Shoes": {
      "ask": 1800000.0,
      "bid": 70000.0
    },
    "Gummy": {
      "ask": 1000000000000.0,
      "bid": 5.0
    },
    "Holy Boots": {
      "ask": 35992.0,
      "bid": 26243.0
    },
    "Holy Brush": {
      "ask": 92997.0,
      "bid": 67000.0
    },
    "Holy Buckler": {
      "ask": 89980.0,
      "bid": 60000.0
    },
    "Holy Bulwark": {
      "ask": 90000.0,
      "bid": 75666.0
    },
    "Holy Cheese": {
      "ask": 595.0,
      "bid": 576.0
    },
    "Holy Enhancer": {
      "ask": 86868.0,
      "bid": 60000.0
    },
    "Holy Gauntlets": {
      "ask": 35967.0,
      "bid": 26324.0
    },
    "Holy Hammer": {
      "ask": 69998.0,
      "bid": 60000.0
    },
    "Holy Helmet": {
      "ask": 50000.0,
      "bid": 37456.0
    },
    "Holy Mace": {
      "ask": 90248.0,
      "bid": 85000.0
    },
    "Holy Milk": {
      "ask": 159.0,
      "bid": 142.0
    },
    "Holy Plate Body": {
      "ask": 95999.0,
      "bid": -1.0
    },
    "Holy Plate Legs": {
      "ask": -1.0,
      "bid": 86000.0
    },
    "Holy Pot": {
      "ask": 69997.0,
      "bid": 60000.0
    },
    "Holy Shears": {
      "ask": 74998.0,
      "bid": 65002.0
    },
    "Holy Spatula": {
      "ask": 66665.0,
      "bid": 60000.0
    },
    "Holy Spear": {
      "ask": 58989.0,
      "bid": 45000.0
    },
    "Holy Sword": {
      "ask": 79800.0,
      "bid": 64001.0
    },
    "Intelligence Coffee": {
      "ask": 295.0,
      "bid": 200.0
    },
    "Large Pouch": {
      "ask": 1500000.0,
      "bid": 750000.0
    },
    "Liberica Coffee Bean": {
      "ask": 139.0,
      "bid": 115.0
    },
    "Lucky Coffee": {
      "ask": 197.0,
      "bid": 90.0
    },
    "Magnifying Glass": {
      "ask": 191256.0,
      "bid": 100005.0
    },
    "Maim": {
      "ask": 1199999.0,
      "bid": 400000.0
    },
    "Marsberry": {
      "ask": 24.0,
      "bid": 20.0
    },
    "Marsberry Cake": {
      "ask": 288.0,
      "bid": 270.0
    },
    "Marsberry Donut": {
      "ask": 498.0,
      "bid": -1.0
    },
    "Medium Pouch": {
      "ask": 61747.0,
      "bid": 26999.0
    },
    "Milk": {
      "ask": 21.0,
      "bid": 10.0
    },
    "Milking Tea": {
      "ask": 271.0,
      "bid": 151.0
    },
    "Mooberry": {
      "ask": 15.0,
      "bid": 11.0
    },
    "Mooberry Cake": {
      "ask": 190.0,
      "bid": 153.0
    },
    "Mooberry Donut": {
      "ask": 274.0,
      "bid": -1.0
    },
    "Moolong Tea Leaf": {
      "ask": 25.0,
      "bid": 20.0
    },
    "Orange": {
      "ask": 6.0,
      "bid": 5.0
    },
    "Orange Gummy": {
      "ask": 150.0,
      "bid": 60.0
    },
    "Orange Yogurt": {
      "ask": 1000000000000.0,
      "bid": 55.0
    },
    "Panda Fluff": {
      "ask": 540141.0,
      "bid": 183005.0
    },
    "Panda Gloves": {
      "ask": -1.0,
      "bid": 1000000.0
    },
    "Peach": {
      "ask": 18.0,
      "bid": 15.0
    },
    "Peach Gummy": {
      "ask": 300.0,
      "bid": 71.0
    },
    "Peach Yogurt": {
      "ask": 199.0,
      "bid": 144.0
    },
    "Pierce": {
      "ask": 19950.0,
      "bid": 3003.0
    },
    "Pincer Gloves": {
      "ask": 149995.0,
      "bid": 35000.0
    },
    "Plum": {
      "ask": 10.0,
      "bid": 6.0
    },
    "Plum Gummy": {
      "ask": 238.0,
      "bid": 70.0
    },
    "Plum Yogurt": {
      "ask": 269.0,
      "bid": 141.0
    },
    "Poke": {
      "ask": 7670.0,
      "bid": 1002.0
    },
    "Polar Bear Fluff": {
      "ask": 99995.0,
      "bid": 70005.0
    },
    "Polar Bear Shoes": {
      "ask": -1.0,
      "bid": 103422.0
    },
    "Power Coffee": {
      "ask": 290.0,
      "bid": 150.0
    },
    "Precision": {
      "ask": 13898.0,
      "bid": 10060.0
    },
    "Rainbow Boots": {
      "ask": 15910.0,
      "bid": 12303.0
    },
    "Rainbow Brush": {
      "ask": 24368.0,
      "bid": 19000.0
    },
    "Rainbow Buckler": {
      "ask": -1.0,
      "bid": -1.0
    },
    "Rainbow Bulwark": {
      "ask": 56858.0,
      "bid": -1.0
    },
    "Rainbow Cheese": {
      "ask": 312.0,
      "bid": 213.0
    },
    "Rainbow Enhancer": {
      "ask": 45123.0,
      "bid": 1.0
    },
    "Rainbow Gauntlets": {
      "ask": 26531.0,
      "bid": 12500.0
    },
    "Rainbow Hammer": {
      "ask": 27500.0,
      "bid": 3.0
    },
    "Rainbow Helmet": {
      "ask": 47000.0,
      "bid": -1.0
    },
    "Rainbow Mace": {
      "ask": 38999.0,
      "bid": 22000.0
    },
    "Rainbow Milk": {
      "ask": 40.0,
      "bid": 33.0
    },
    "Rainbow Plate Body": {
      "ask": 33000.0,
      "bid": -1.0
    },
    "Rainbow Plate Legs": {
      "ask": 42738.0,
      "bid": 22001.0
    },
    "Rainbow Pot": {
      "ask": 52999.0,
      "bid": 2.0
    },
    "Rainbow Shears": {
      "ask": -1.0,
      "bid": 100.0
    },
    "Rainbow Spatula": {
      "ask": 33739.0,
      "bid": 2.0
    },
    "Rainbow Spear": {
      "ask": -1.0,
      "bid": 15000.0
    },
    "Rainbow Sword": {
      "ask": 26997.0,
      "bid": 17982.0
    },
    "Red Tea Leaf": {
      "ask": 262.0,
      "bid": 215.5
    },
    "Robusta Coffee Bean": {
      "ask": 97.0,
      "bid": 88.0
    },
    "Scratch": {
      "ask": 28038.0,
      "bid": 10007.0
    },
    "Smack": {
      "ask": 27882.0,
      "bid": 21006.0
    },
    "Small Pouch": {
      "ask": 8999.0,
      "bid": 23.0
    },
    "Snail Shell": {
      "ask": 3735.0,
      "bid": 2600.0
    },
    "Snail Shell Helmet": {
      "ask": 6123.0,
      "bid": 5000.0
    },
    "Snake Fang": {
      "ask": 1139.0,
      "bid": 500.0
    },
    "Snake Fang Dirk": {
      "ask": 8550.0,
      "bid": 3016.0
    },
    "Spaceberry": {
      "ask": 89.0,
      "bid": 58.0
    },
    "Spaceberry Cake": {
      "ask": 608.5,
      "bid": 535.0
    },
    "Spaceberry Donut": {
      "ask": 644.0,
      "bid": 300.5
    },
    "Spacia Coffee Bean": {
      "ask": 188.0,
      "bid": 162.0
    },
    "Stamina Coffee": {
      "ask": 200.0,
      "bid": 100.0
    },
    "Star Fruit": {
      "ask": 224.0,
      "bid": 94.0
    },
    "Star Fruit Gummy": {
      "ask": 900.0,
      "bid": 105.0
    },
    "Star Fruit Yogurt": {
      "ask": 681.0,
      "bid": 609.0
    },
    "Strawberry": {
      "ask": 29.0,
      "bid": 24.0
    },
    "Strawberry Cake": {
      "ask": 244.0,
      "bid": 90.0
    },
    "Strawberry Donut": {
      "ask": 183.5,
      "bid": 35.0
    },
    "Sugar": {
      "ask": 4.0,
      "bid": 3.0
    },
    "Super Attack Coffee": {
      "ask": 518.5,
      "bid": 406.0
    },
    "Super Brewing Tea": {
      "ask": 495.0,
      "bid": 101.0
    },
    "Super Cheesesmithing Tea": {
      "ask": 880.0,
      "bid": 526.0
    },
    "Super Cooking Tea": {
      "ask": 657.0,
      "bid": 150.0
    },
    "Super Defense Coffee": {
      "ask": 500.0,
      "bid": 100.0
    },
    "Super Enhancing Tea": {
      "ask": 554.0,
      "bid": 425.0
    },
    "Super Foraging Tea": {
      "ask": 279.0,
      "bid": 150.0
    },
    "Super Intelligence Coffee": {
      "ask": 389.0,
      "bid": 224.0
    },
    "Super Milking Tea": {
      "ask": 550.0,
      "bid": 102.0
    },
    "Super Power Coffee": {
      "ask": 478.0,
      "bid": 448.0
    },
    "Super Stamina Coffee": {
      "ask": 410.0,
      "bid": 200.0
    },
    "Swamp Essence": {
      "ask": 35.0,
      "bid": 26.0
    },
    "Sweep": {
      "ask": 182398.0,
      "bid": 130012.0
    },
    "Swiftness Coffee": {
      "ask": 609.0,
      "bid": 431.0
    },
    "Toughness": {
      "ask": 23000.0,
      "bid": 7500.5
    },
    "Turtle Shell": {
      "ask": 20000.0,
      "bid": 3002.0
    },
    "Turtle Shell Body": {
      "ask": 39999.0,
      "bid": -1.0
    },
    "Turtle Shell Legs": {
      "ask": 30000.0,
      "bid": -1.0
    },
    "Twilight Essence": {
      "ask": 222.0,
      "bid": 201.0
    },
    "Vampire Fang": {
      "ask": 1840000.0,
      "bid": 1260000.0
    },
    "Vampire Fang Dirk": {
      "ask": -1.0,
      "bid": 244.5
    },
    "Vampirism": {
      "ask": 490000.0,
      "bid": 108520.0
    },
    "Verdant Boots": {
      "ask": -1.0,
      "bid": -1.0
    },
    "Verdant Brush": {
      "ask": -1.0,
      "bid": 700.0
    },
    "Verdant Buckler": {
      "ask": -1.0,
      "bid": 420.0
    },
    "Verdant Bulwark": {
      "ask": 6969.0,
      "bid": 1236.0
    },
    "Verdant Cheese": {
      "ask": 136.0,
      "bid": 112.0
    },
    "Verdant Enhancer": {
      "ask": 3000.0,
      "bid": 400.0
    },
    "Verdant Gauntlets": {
      "ask": -1.0,
      "bid": 380.0
    },
    "Verdant Hammer": {
      "ask": 2400.0,
      "bid": 362.0
    },
    "Verdant Helmet": {
      "ask": -1.0,
      "bid": 800.0
    },
    "Verdant Mace": {
      "ask": 25000.0,
      "bid": -1.0
    },
    "Verdant Milk": {
      "ask": 30.0,
      "bid": 26.0
    },
    "Verdant Plate Body": {
      "ask": 14999.0,
      "bid": 605.0
    },
    "Verdant Plate Legs": {
      "ask": 18000.0,
      "bid": 455.0
    },
    "Verdant Pot": {
      "ask": 3559.0,
      "bid": 445.0
    },
    "Verdant Shears": {
      "ask": 3792.0,
      "bid": 435.0
    },
    "Verdant Spatula": {
      "ask": 3500.0,
      "bid": 465.0
    },
    "Verdant Spear": {
      "ask": 4500.0,
      "bid": 385.0
    },
    "Verdant Sword": {
      "ask": -1.0,
      "bid": 420.0
    },
    "Vision Helmet": {
      "ask": 299998.0,
      "bid": 75000.0
    },
    "Vision Shield": {
      "ask": 300000.0,
      "bid": 100000.0
    },
    "Werewolf Claw": {
      "ask": 1149995.0,
      "bid": 1060010.0
    },
    "Werewolf Slasher": {
      "ask": -1.0,
      "bid": 15000000.0
    },
    "Wheat": {
      "ask": 15.0,
      "bid": 11.0
    },
    "Wisdom Tea": {
      "ask": 626.0,
      "bid": 566.5
    },
    "Yogurt": {
      "ask": 999.0,
      "bid": 50.0
    }
  }
}