{
  "market": {
    "Apple": {
      "ask": 11,
      "bid": 6,
      "vendor": 2
    },
    "Apple Gummy": {
      "ask": 11,
      "bid": 10,
      "vendor": 10
    },
    "Apple Yogurt": {
      "ask": 45,
      "bid": 17,
      "vendor": 10
    },
    "Aqua Arrow": {
      "ask": 1424996,
      "bid": 176428,
      "vendor": 1000
    },
    "Aqua Essence": {
      "ask": 30,
      "bid": 18,
      "vendor": 16
    },
    "Arabica Coffee Bean": {
      "ask": 118,
      "bid": 97,
      "vendor": 4
    },
    "Arcane Bow": {
      "ask": 209000,
      "bid": 115000,
      "vendor": 106920
    },
    "Arcane Crossbow": {
      "ask": 250000,
      "bid": -1,
      "vendor": 80190
    },
    "Arcane Fire Staff": {
      "ask": 180500,
      "bid": 105001,
      "vendor": 80190
    },
    "Arcane Log": {
      "ask": 205,
      "bid": 130,
      "vendor": 54
    },
    "Arcane Lumber": {
      "ask": 1005,
      "bid": 600,
      "vendor": 162
    },
    "Arcane Nature Staff": {
      "ask": 2751678,
      "bid": 210000,
      "vendor": 80190
    },
    "Arcane Water Staff": {
      "ask": 390490,
      "bid": -1,
      "vendor": 80190
    },
    "Artisan Tea": {
      "ask": 1794,
      "bid": 815,
      "vendor": 75
    },
    "Attack Coffee": {
      "ask": 349,
      "bid": 282,
      "vendor": 20
    },
    "Azure Boots": {
      "ask": 14000,
      "bid": -1,
      "vendor": 864
    },
    "Azure Brush": {
      "ask": 35000,
      "bid": 1160,
      "vendor": 1512
    },
    "Azure Buckler": {
      "ask": -1,
      "bid": 1350,
      "vendor": 1296
    },
    "Azure Bulwark": {
      "ask": 30000,
      "bid": -1,
      "vendor": 2592
    },
    "Azure Cheese": {
      "ask": 354,
      "bid": 153,
      "vendor": 24
    },
    "Azure Chisel": {
      "ask": 27500,
      "bid": -1,
      "vendor": 1512
    },
    "Azure Enhancer": {
      "ask": 16598,
      "bid": 1800,
      "vendor": 1512
    },
    "Azure Gauntlets": {
      "ask": 8000,
      "bid": 1131,
      "vendor": 864
    },
    "Azure Hammer": {
      "ask": 15000,
      "bid": 1435,
      "vendor": 1512
    },
    "Azure Hatchet": {
      "ask": 25000,
      "bid": -1,
      "vendor": 1512
    },
    "Azure Helmet": {
      "ask": 20000,
      "bid": 3604,
      "vendor": 1080
    },
    "Azure Mace": {
      "ask": 14250,
      "bid": 3500,
      "vendor": 1944
    },
    "Azure Milk": {
      "ask": 68,
      "bid": 45,
      "vendor": 8
    },
    "Azure Needle": {
      "ask": 20000,
      "bid": -1,
      "vendor": 1512
    },
    "Azure Plate Body": {
      "ask": 14000,
      "bid": -1,
      "vendor": 1728
    },
    "Azure Plate Legs": {
      "ask": -1,
      "bid": -1,
      "vendor": 1512
    },
    "Azure Pot": {
      "ask": 12886,
      "bid": 1155,
      "vendor": 1512
    },
    "Azure Shears": {
      "ask": 17000,
      "bid": -1,
      "vendor": 1512
    },
    "Azure Spatula": {
      "ask": -1,
      "bid": 3000,
      "vendor": 1512
    },
    "Azure Spear": {
      "ask": 15000,
      "bid": 3000,
      "vendor": 1944
    },
    "Azure Sword": {
      "ask": 25000,
      "bid": 1874,
      "vendor": 1944
    },
    "Bamboo Boots": {
      "ask": 28996,
      "bid": 2500,
      "vendor": 1872
    },
    "Bamboo Branch": {
      "ask": 142,
      "bid": 32,
      "vendor": 12
    },
    "Bamboo Fabric": {
      "ask": 598,
      "bid": 484,
      "vendor": 36
    },
    "Bamboo Gloves": {
      "ask": 29998,
      "bid": -1,
      "vendor": 1872
    },
    "Bamboo Hat": {
      "ask": 32999,
      "bid": -1,
      "vendor": 2340
    },
    "Bamboo Robe Bottoms": {
      "ask": 21998,
      "bid": 8007,
      "vendor": 3276
    },
    "Bamboo Robe Top": {
      "ask": 22550,
      "bid": 10013,
      "vendor": 3744
    },
    "Bear Essence": {
      "ask": 55,
      "bid": 54,
      "vendor": 54
    },
    "Beast Boots": {
      "ask": 45800,
      "bid": 26250,
      "vendor": 7200
    },
    "Beast Bracers": {
      "ask": 53556,
      "bid": -1,
      "vendor": 7200
    },
    "Beast Chaps": {
      "ask": 124700,
      "bid": -1,
      "vendor": 12600
    },
    "Beast Hide": {
      "ask": 200,
      "bid": 86,
      "vendor": 24
    },
    "Beast Hood": {
      "ask": 32299,
      "bid": -1,
      "vendor": 9000
    },
    "Beast Leather": {
      "ask": 772,
      "bid": 403,
      "vendor": 72
    },
    "Beast Tunic": {
      "ask": 262751,
      "bid": -1,
      "vendor": 14400
    },
    "Berserk": {
      "ask": 298229,
      "bid": 175002,
      "vendor": 1000
    },
    "Birch Bow": {
      "ask": -1,
      "bid": -1,
      "vendor": 720
    },
    "Birch Crossbow": {
      "ask": 29997,
      "bid": -1,
      "vendor": 540
    },
    "Birch Fire Staff": {
      "ask": 114000,
      "bid": -1,
      "vendor": 540
    },
    "Birch Log": {
      "ask": 111,
      "bid": 57,
      "vendor": 4
    },
    "Birch Lumber": {
      "ask": 86,
      "bid": 61,
      "vendor": 12
    },
    "Birch Nature Staff": {
      "ask": 9025,
      "bid": -1,
      "vendor": 540
    },
    "Birch Water Staff": {
      "ask": 36648,
      "bid": -1,
      "vendor": 540
    },
    "Black Bear Fluff": {
      "ask": 22562,
      "bid": 5401,
      "vendor": 3000
    },
    "Black Bear Shoes": {
      "ask": 100000,
      "bid": 1,
      "vendor": 60000
    },
    "Black Tea Leaf": {
      "ask": 31,
      "bid": 30,
      "vendor": 8
    },
    "Blackberry": {
      "ask": 27,
      "bid": 18,
      "vendor": 4
    },
    "Blackberry Cake": {
      "ask": 199,
      "bid": 100,
      "vendor": 20
    },
    "Blackberry Donut": {
      "ask": 168,
      "bid": 74,
      "vendor": 20
    },
    "Blessed Tea": {
      "ask": 1155,
      "bid": 463,
      "vendor": 75
    },
    "Blueberry": {
      "ask": 13,
      "bid": 11,
      "vendor": 2
    },
    "Blueberry Cake": {
      "ask": 100,
      "bid": 19,
      "vendor": 10
    },
    "Blueberry Donut": {
      "ask": 50,
      "bid": 11,
      "vendor": 10
    },
    "Brewing Tea": {
      "ask": 175,
      "bid": 30,
      "vendor": 20
    },
    "Burble Boots": {
      "ask": -1,
      "bid": -1,
      "vendor": 2160
    },
    "Burble Brush": {
      "ask": 50000,
      "bid": 4005,
      "vendor": 3780
    },
    "Burble Buckler": {
      "ask": 20000,
      "bid": -1,
      "vendor": 3240
    },
    "Burble Bulwark": {
      "ask": 6480,
      "bid": 1,
      "vendor": 6480
    },
    "Burble Cheese": {
      "ask": 349,
      "bid": 229,
      "vendor": 36
    },
    "Burble Chisel": {
      "ask": 50000,
      "bid": -1,
      "vendor": 3780
    },
    "Burble Enhancer": {
      "ask": 50000,
      "bid": 3008,
      "vendor": 3780
    },
    "Burble Gauntlets": {
      "ask": 25000,
      "bid": -1,
      "vendor": 2160
    },
    "Burble Hammer": {
      "ask": 27075,
      "bid": 105,
      "vendor": 3780
    },
    "Burble Hatchet": {
      "ask": 47500,
      "bid": -1,
      "vendor": 3780
    },
    "Burble Helmet": {
      "ask": -1,
      "bid": 2805,
      "vendor": 2700
    },
    "Burble Mace": {
      "ask": 17400,
      "bid": 1000,
      "vendor": 4860
    },
    "Burble Milk": {
      "ask": 43,
      "bid": 34,
      "vendor": 12
    },
    "Burble Needle": {
      "ask": 45000,
      "bid": -1,
      "vendor": 3780
    },
    "Burble Plate Body": {
      "ask": 49000,
      "bid": 5253,
      "vendor": 4320
    },
    "Burble Plate Legs": {
      "ask": -1,
      "bid": 1500,
      "vendor": 3780
    },
    "Burble Pot": {
      "ask": 45000,
      "bid": 3155,
      "vendor": 3780
    },
    "Burble Shears": {
      "ask": 45000,
      "bid": 3360,
      "vendor": 3780
    },
    "Burble Spatula": {
      "ask": 50000,
      "bid": 3500,
      "vendor": 3780
    },
    "Burble Spear": {
      "ask": 79000,
      "bid": 1000,
      "vendor": 4860
    },
    "Burble Sword": {
      "ask": -1,
      "bid": -1,
      "vendor": 4860
    },
    "Burble Tea Leaf": {
      "ask": 332,
      "bid": 260,
      "vendor": 12
    },
    "Cedar Bow": {
      "ask": 19999,
      "bid": 5000,
      "vendor": 2592
    },
    "Cedar Crossbow": {
      "ask": 75000,
      "bid": -1,
      "vendor": 1944
    },
    "Cedar Fire Staff": {
      "ask": 50000,
      "bid": -1,
      "vendor": 1944
    },
    "Cedar Log": {
      "ask": 100,
      "bid": 38,
      "vendor": 8
    },
    "Cedar Lumber": {
      "ask": 297,
      "bid": 195,
      "vendor": 24
    },
    "Cedar Nature Staff": {
      "ask": 50000,
      "bid": -1,
      "vendor": 1944
    },
    "Cedar Water Staff": {
      "ask": 50000,
      "bid": -1,
      "vendor": 1944
    },
    "Centaur Boots": {
      "ask": 900000,
      "bid": -1,
      "vendor": 50000
    },
    "Centaur Hoof": {
      "ask": 71244,
      "bid": 42004,
      "vendor": 3000
    },
    "Cheese": {
      "ask": 92,
      "bid": 86,
      "vendor": 6
    },
    "Cheese Boots": {
      "ask": 1600,
      "bid": -1,
      "vendor": 48
    },
    "Cheese Brush": {
      "ask": 3599,
      "bid": 310,
      "vendor": 84
    },
    "Cheese Buckler": {
      "ask": 2500,
      "bid": 216,
      "vendor": 72
    },
    "Cheese Bulwark": {
      "ask": 2843,
      "bid": -1,
      "vendor": 144
    },
    "Cheese Chisel": {
      "ask": 4750,
      "bid": -1,
      "vendor": 84
    },
    "Cheese Enhancer": {
      "ask": -1,
      "bid": 301,
      "vendor": 84
    },
    "Cheese Gauntlets": {
      "ask": 800,
      "bid": -1,
      "vendor": 48
    },
    "Cheese Hammer": {
      "ask": 1800,
      "bid": 301,
      "vendor": 84
    },
    "Cheese Hatchet": {
      "ask": 5000,
      "bid": -1,
      "vendor": 84
    },
    "Cheese Helmet": {
      "ask": 2000,
      "bid": 270,
      "vendor": 60
    },
    "Cheese Mace": {
      "ask": 2000,
      "bid": 180,
      "vendor": 108
    },
    "Cheese Needle": {
      "ask": 6000,
      "bid": -1,
      "vendor": 84
    },
    "Cheese Plate Body": {
      "ask": 3999,
      "bid": 1000,
      "vendor": 96
    },
    "Cheese Plate Legs": {
      "ask": 3000,
      "bid": 279,
      "vendor": 84
    },
    "Cheese Pot": {
      "ask": 7000,
      "bid": 160,
      "vendor": 84
    },
    "Cheese Shears": {
      "ask": 1799,
      "bid": 85,
      "vendor": 84
    },
    "Cheese Spatula": {
      "ask": 1000000,
      "bid": 160,
      "vendor": 84
    },
    "Cheese Spear": {
      "ask": 3000,
      "bid": 251,
      "vendor": 108
    },
    "Cheese Sword": {
      "ask": 1500,
      "bid": 166,
      "vendor": 108
    },
    "Cheesesmithing Tea": {
      "ask": 711,
      "bid": 310,
      "vendor": 30
    },
    "Cleave": {
      "ask": 168981,
      "bid": 100020,
      "vendor": 1000
    },
    "Cocoon": {
      "ask": 175,
      "bid": 36,
      "vendor": 24
    },
    "Coin": {
      "ask": -1,
      "bid": -1,
      "vendor": 0
    },
    "Cooking Tea": {
      "ask": 220,
      "bid": 106,
      "vendor": 20
    },
    "Cotton": {
      "ask": 262,
      "bid": 54,
      "vendor": 2
    },
    "Cotton Boots": {
      "ask": 1400,
      "bid": -1,
      "vendor": 48
    },
    "Cotton Fabric": {
      "ask": 202,
      "bid": 114,
      "vendor": 6
    },
    "Cotton Gloves": {
      "ask": 2250,
      "bid": -1,
      "vendor": 48
    },
    "Cotton Hat": {
      "ask": 13070,
      "bid": -1,
      "vendor": 60
    },
    "Cotton Robe Bottoms": {
      "ask": 3000,
      "bid": 1608,
      "vendor": 84
    },
    "Cotton Robe Top": {
      "ask": 5141,
      "bid": 903,
      "vendor": 96
    },
    "Cowbell": {
      "ask": -1,
      "bid": -1,
      "vendor": 0
    },
    "Crab Pincer": {
      "ask": 50000,
      "bid": 40015,
      "vendor": 1500
    },
    "Crafting Tea": {
      "ask": 800,
      "bid": 450,
      "vendor": 30
    },
    "Crimson Boots": {
      "ask": 25000,
      "bid": 5715,
      "vendor": 5184
    },
    "Crimson Brush": {
      "ask": 40000,
      "bid": 10004,
      "vendor": 9072
    },
    "Crimson Buckler": {
      "ask": 75000,
      "bid": 15000,
      "vendor": 7776
    },
    "Crimson Bulwark": {
      "ask": 23749,
      "bid": 15552,
      "vendor": 15552
    },
    "Crimson Cheese": {
      "ask": 337,
      "bid": 229,
      "vendor": 54
    },
    "Crimson Chisel": {
      "ask": 40000,
      "bid": -1,
      "vendor": 9072
    },
    "Crimson Enhancer": {
      "ask": 39999,
      "bid": 10002,
      "vendor": 9072
    },
    "Crimson Gauntlets": {
      "ask": 49875,
      "bid": 5503,
      "vendor": 5184
    },
    "Crimson Hammer": {
      "ask": 39000,
      "bid": 6810,
      "vendor": 9072
    },
    "Crimson Hatchet": {
      "ask": 40000,
      "bid": -1,
      "vendor": 9072
    },
    "Crimson Helmet": {
      "ask": 30000,
      "bid": 10000,
      "vendor": 6480
    },
    "Crimson Mace": {
      "ask": 33250,
      "bid": -1,
      "vendor": 11664
    },
    "Crimson Milk": {
      "ask": 39,
      "bid": 20,
      "vendor": 18
    },
    "Crimson Needle": {
      "ask": 40000,
      "bid": -1,
      "vendor": 9072
    },
    "Crimson Plate Body": {
      "ask": 45000,
      "bid": 17500,
      "vendor": 10368
    },
    "Crimson Plate Legs": {
      "ask": -1,
      "bid": -1,
      "vendor": 9072
    },
    "Crimson Pot": {
      "ask": 40000,
      "bid": 6815,
      "vendor": 9072
    },
    "Crimson Shears": {
      "ask": 40000,
      "bid": -1,
      "vendor": 9072
    },
    "Crimson Spatula": {
      "ask": 40000,
      "bid": 6810,
      "vendor": 9072
    },
    "Crimson Spear": {
      "ask": -1,
      "bid": 11081,
      "vendor": 11664
    },
    "Crimson Sword": {
      "ask": 26535,
      "bid": 3000,
      "vendor": 11664
    },
    "Cupcake": {
      "ask": 38,
      "bid": 5,
      "vendor": 5
    },
    "Defense Coffee": {
      "ask": 250,
      "bid": 183,
      "vendor": 20
    },
    "Donut": {
      "ask": 15,
      "bid": 1,
      "vendor": 5
    },
    "Dragon Fruit": {
      "ask": 69,
      "bid": 56,
      "vendor": 14
    },
    "Dragon Fruit Gummy": {
      "ask": 507,
      "bid": 359,
      "vendor": 50
    },
    "Dragon Fruit Yogurt": {
      "ask": 448,
      "bid": 361,
      "vendor": 50
    },
    "Efficiency Tea": {
      "ask": 1829,
      "bid": 1255,
      "vendor": 50
    },
    "Egg": {
      "ask": 30,
      "bid": 11,
      "vendor": 1
    },
    "Elemental Affinity": {
      "ask": 799988,
      "bid": 300206,
      "vendor": 1000
    },
    "Emp Tea Leaf": {
      "ask": 324,
      "bid": 259,
      "vendor": 54
    },
    "Enhancing Tea": {
      "ask": 332,
      "bid": 217,
      "vendor": 20
    },
    "Entangle": {
      "ask": 29000,
      "bid": 5019,
      "vendor": 1000
    },
    "Excelsa Coffee Bean": {
      "ask": 109,
      "bid": 100,
      "vendor": 18
    },
    "Eyessence": {
      "ask": 53,
      "bid": 45,
      "vendor": 36
    },
    "Fermenting Tea": {
      "ask": 895,
      "bid": 501,
      "vendor": 40
    },
    "Fieriosa Coffee Bean": {
      "ask": 194,
      "bid": 121,
      "vendor": 27
    },
    "Fireball": {
      "ask": 22997,
      "bid": 15023,
      "vendor": 1000
    },
    "Flame Arrow": {
      "ask": 300000,
      "bid": 150033,
      "vendor": 1000
    },
    "Flame Blast": {
      "ask": 721977,
      "bid": 550005,
      "vendor": 1000
    },
    "Flaming Cloth": {
      "ask": 161679,
      "bid": 125000,
      "vendor": 4000
    },
    "Flaming Robe Bottoms": {
      "ask": 1649999,
      "bid": -1,
      "vendor": 40000
    },
    "Flaming Robe Top": {
      "ask": 2049999,
      "bid": 750000,
      "vendor": 60000
    },
    "Flax": {
      "ask": 90,
      "bid": 21,
      "vendor": 6
    },
    "Foraging Tea": {
      "ask": 493,
      "bid": 211,
      "vendor": 10
    },
    "Frenzy": {
      "ask": 121999,
      "bid": 35036,
      "vendor": 1000
    },
    "Gathering Tea": {
      "ask": 941,
      "bid": 455,
      "vendor": 10
    },
    "Gator Vest": {
      "ask": 21434,
      "bid": 19002,
      "vendor": 5000
    },
    "Giant Pouch": {
      "ask": 7281739,
      "bid": 3000001,
      "vendor": 5000000
    },
    "Ginkgo Bow": {
      "ask": 50548,
      "bid": -1,
      "vendor": 15552
    },
    "Ginkgo Crossbow": {
      "ask": 72513,
      "bid": -1,
      "vendor": 11664
    },
    "Ginkgo Fire Staff": {
      "ask": 56431,
      "bid": -1,
      "vendor": 11664
    },
    "Ginkgo Log": {
      "ask": 68,
      "bid": 28,
      "vendor": 18
    },
    "Ginkgo Lumber": {
      "ask": 397,
      "bid": 250,
      "vendor": 54
    },
    "Ginkgo Nature Staff": {
      "ask": 198000,
      "bid": 45000,
      "vendor": 11664
    },
    "Ginkgo Water Staff": {
      "ask": 160050,
      "bid": -1,
      "vendor": 11664
    },
    "Gobo Boomstick": {
      "ask": 57000,
      "bid": 15000,
      "vendor": 20000
    },
    "Gobo Boots": {
      "ask": 29751,
      "bid": 4501,
      "vendor": 1872
    },
    "Gobo Bracers": {
      "ask": 17447,
      "bid": 1966,
      "vendor": 1872
    },
    "Gobo Chaps": {
      "ask": -1,
      "bid": 4604,
      "vendor": 3276
    },
    "Gobo Essence": {
      "ask": 25,
      "bid": 20,
      "vendor": 24
    },
    "Gobo Hide": {
      "ask": 130,
      "bid": 69,
      "vendor": 12
    },
    "Gobo Hood": {
      "ask": 10523,
      "bid": 2457,
      "vendor": 2340
    },
    "Gobo Leather": {
      "ask": 609,
      "bid": 301,
      "vendor": 36
    },
    "Gobo Shooter": {
      "ask": 24420,
      "bid": 15000,
      "vendor": 20000
    },
    "Gobo Slasher": {
      "ask": 22561,
      "bid": 3000,
      "vendor": 20000
    },
    "Gobo Smasher": {
      "ask": 23737,
      "bid": 1,
      "vendor": 20000
    },
    "Gobo Stabber": {
      "ask": 24500,
      "bid": 5000,
      "vendor": 20000
    },
    "Gobo Tunic": {
      "ask": 142497,
      "bid": 3931,
      "vendor": 3744
    },
    "Goggles": {
      "ask": 150000,
      "bid": 10001,
      "vendor": 10000
    },
    "Golem Essence": {
      "ask": 399,
      "bid": 266,
      "vendor": 108
    },
    "Gourmet Tea": {
      "ask": 406,
      "bid": 350,
      "vendor": 20
    },
    "Granite Bludgeon": {
      "ask": -1,
      "bid": 5000000,
      "vendor": 400000
    },
    "Green Tea Leaf": {
      "ask": 64,
      "bid": 54,
      "vendor": 4
    },
    "Grizzly Bear Fluff": {
      "ask": 69820,
      "bid": 65000,
      "vendor": 3000
    },
    "Grizzly Bear Shoes": {
      "ask": 750000,
      "bid": 65000,
      "vendor": 60000
    },
    "Gummy": {
      "ask": 20,
      "bid": 11,
      "vendor": 5
    },
    "Heal": {
      "ask": 748999,
      "bid": 25008,
      "vendor": 1000
    },
    "Holy Boots": {
      "ask": 35950,
      "bid": 31465,
      "vendor": 35640
    },
    "Holy Brush": {
      "ask": 120000,
      "bid": 100,
      "vendor": 62370
    },
    "Holy Buckler": {
      "ask": 80000,
      "bid": -1,
      "vendor": 53460
    },
    "Holy Bulwark": {
      "ask": 110000,
      "bid": 101123,
      "vendor": 106920
    },
    "Holy Cheese": {
      "ask": 765,
      "bid": 707,
      "vendor": 162
    },
    "Holy Chisel": {
      "ask": 180000,
      "bid": -1,
      "vendor": 62370
    },
    "Holy Enhancer": {
      "ask": 125000,
      "bid": 85001,
      "vendor": 62370
    },
    "Holy Gauntlets": {
      "ask": 39520,
      "bid": 25444,
      "vendor": 35640
    },
    "Holy Hammer": {
      "ask": 149450,
      "bid": 51,
      "vendor": 62370
    },
    "Holy Hatchet": {
      "ask": 113999,
      "bid": 100000,
      "vendor": 62370
    },
    "Holy Helmet": {
      "ask": 64750,
      "bid": 33222,
      "vendor": 44550
    },
    "Holy Mace": {
      "ask": 89995,
      "bid": -1,
      "vendor": 80190
    },
    "Holy Milk": {
      "ask": 260,
      "bid": 246,
      "vendor": 54
    },
    "Holy Needle": {
      "ask": 147900,
      "bid": -1,
      "vendor": 62370
    },
    "Holy Plate Body": {
      "ask": 115000,
      "bid": 58111,
      "vendor": 71280
    },
    "Holy Plate Legs": {
      "ask": -1,
      "bid": 73050,
      "vendor": 62370
    },
    "Holy Pot": {
      "ask": 150000,
      "bid": 105000,
      "vendor": 62370
    },
    "Holy Shears": {
      "ask": -1,
      "bid": 100001,
      "vendor": 62370
    },
    "Holy Spatula": {
      "ask": 129999,
      "bid": 65555,
      "vendor": 62370
    },
    "Holy Spear": {
      "ask": 81977,
      "bid": -1,
      "vendor": 80190
    },
    "Holy Sword": {
      "ask": 109900,
      "bid": 82000,
      "vendor": 80190
    },
    "Ice Spear": {
      "ask": 599980,
      "bid": 300003,
      "vendor": 1000
    },
    "Icy Cloth": {
      "ask": 449998,
      "bid": 75000,
      "vendor": 4000
    },
    "Icy Robe Bottoms": {
      "ask": 1800000,
      "bid": -1,
      "vendor": 40000
    },
    "Icy Robe Top": {
      "ask": 2000000,
      "bid": -1,
      "vendor": 60000
    },
    "Intelligence Coffee": {
      "ask": 367,
      "bid": 254,
      "vendor": 10
    },
    "Jungle Essence": {
      "ask": 93,
      "bid": 50,
      "vendor": 24
    },
    "Large Pouch": {
      "ask": 1341351,
      "bid": 512004,
      "vendor": 500000
    },
    "Liberica Coffee Bean": {
      "ask": 398,
      "bid": 308,
      "vendor": 12
    },
    "Linen Boots": {
      "ask": 24739,
      "bid": 3000,
      "vendor": 432
    },
    "Linen Fabric": {
      "ask": 465,
      "bid": 381,
      "vendor": 18
    },
    "Linen Gloves": {
      "ask": 10999,
      "bid": -1,
      "vendor": 432
    },
    "Linen Hat": {
      "ask": 20000,
      "bid": -1,
      "vendor": 540
    },
    "Linen Robe Bottoms": {
      "ask": 15999,
      "bid": 4000,
      "vendor": 756
    },
    "Linen Robe Top": {
      "ask": 20000,
      "bid": 6000,
      "vendor": 864
    },
    "Living Granite": {
      "ask": 968485,
      "bid": 439001,
      "vendor": 10000
    },
    "Log": {
      "ask": 24,
      "bid": 9,
      "vendor": 2
    },
    "Lucky Coffee": {
      "ask": 375,
      "bid": 298,
      "vendor": 40
    },
    "Lumber": {
      "ask": 197,
      "bid": 25,
      "vendor": 6
    },
    "Magic Coffee": {
      "ask": 558,
      "bid": 251,
      "vendor": 30
    },
    "Magnet": {
      "ask": 499999,
      "bid": 175000,
      "vendor": 10000
    },
    "Magnetic Gloves": {
      "ask": -1,
      "bid": 2000000,
      "vendor": 300000
    },
    "Magnifying Glass": {
      "ask": 159000,
      "bid": 10001,
      "vendor": 10000
    },
    "Maim": {
      "ask": 286214,
      "bid": 157799,
      "vendor": 1000
    },
    "Marsberry": {
      "ask": 36,
      "bid": 31,
      "vendor": 14
    },
    "Marsberry Cake": {
      "ask": 348,
      "bid": 277,
      "vendor": 50
    },
    "Marsberry Donut": {
      "ask": 428,
      "bid": 345,
      "vendor": 50
    },
    "Medium Pouch": {
      "ask": 74813,
      "bid": 2,
      "vendor": 50000
    },
    "Milk": {
      "ask": 13,
      "bid": 12,
      "vendor": 2
    },
    "Milking Tea": {
      "ask": 570,
      "bid": 175,
      "vendor": 10
    },
    "Minor Heal": {
      "ask": 13000,
      "bid": 3512,
      "vendor": 1000
    },
    "Mooberry": {
      "ask": 29,
      "bid": 15,
      "vendor": 9
    },
    "Mooberry Cake": {
      "ask": 283,
      "bid": 164,
      "vendor": 40
    },
    "Mooberry Donut": {
      "ask": 348,
      "bid": 172,
      "vendor": 40
    },
    "Moolong Tea Leaf": {
      "ask": 32,
      "bid": 27,
      "vendor": 18
    },
    "Orange": {
      "ask": 9,
      "bid": 8,
      "vendor": 4
    },
    "Orange Gummy": {
      "ask": 25,
      "bid": 20,
      "vendor": 20
    },
    "Orange Yogurt": {
      "ask": 119,
      "bid": 21,
      "vendor": 20
    },
    "Panda Fluff": {
      "ask": 30946,
      "bid": 2,
      "vendor": 3000
    },
    "Panda Gloves": {
      "ask": 721998,
      "bid": 250000,
      "vendor": 60000
    },
    "Peach": {
      "ask": 35,
      "bid": 19,
      "vendor": 9
    },
    "Peach Gummy": {
      "ask": 312,
      "bid": 214,
      "vendor": 40
    },
    "Peach Yogurt": {
      "ask": 423,
      "bid": 177,
      "vendor": 40
    },
    "Pierce": {
      "ask": 34999,
      "bid": 12010,
      "vendor": 1000
    },
    "Pincer Gloves": {
      "ask": 177000,
      "bid": 71026,
      "vendor": 6000
    },
    "Plum": {
      "ask": 33,
      "bid": 28,
      "vendor": 6
    },
    "Plum Gummy": {
      "ask": 119,
      "bid": 68,
      "vendor": 30
    },
    "Plum Yogurt": {
      "ask": 380,
      "bid": 184,
      "vendor": 30
    },
    "Poke": {
      "ask": 1199,
      "bid": 704,
      "vendor": 1000
    },
    "Polar Bear Fluff": {
      "ask": 44451,
      "bid": 5001,
      "vendor": 3000
    },
    "Polar Bear Shoes": {
      "ask": 1300000,
      "bid": 120000,
      "vendor": 60000
    },
    "Power Coffee": {
      "ask": 599,
      "bid": 426,
      "vendor": 30
    },
    "Precision": {
      "ask": 28996,
      "bid": 10000,
      "vendor": 1000
    },
    "Purpleheart Bow": {
      "ask": 27075,
      "bid": 7801,
      "vendor": 6480
    },
    "Purpleheart Crossbow": {
      "ask": 47494,
      "bid": -1,
      "vendor": 4860
    },
    "Purpleheart Fire Staff": {
      "ask": 39999,
      "bid": -1,
      "vendor": 4860
    },
    "Purpleheart Log": {
      "ask": 42,
      "bid": 21,
      "vendor": 12
    },
    "Purpleheart Lumber": {
      "ask": 392,
      "bid": 214,
      "vendor": 36
    },
    "Purpleheart Nature Staff": {
      "ask": 199500,
      "bid": -1,
      "vendor": 4860
    },
    "Purpleheart Water Staff": {
      "ask": 99250,
      "bid": -1,
      "vendor": 4860
    },
    "Quick Shot": {
      "ask": 29992,
      "bid": 15000,
      "vendor": 1000
    },
    "Radiant Boots": {
      "ask": 500000,
      "bid": 1,
      "vendor": 24768
    },
    "Radiant Fabric": {
      "ask": 1000,
      "bid": 650,
      "vendor": 144
    },
    "Radiant Fiber": {
      "ask": 148,
      "bid": 114,
      "vendor": 48
    },
    "Radiant Gloves": {
      "ask": 899955,
      "bid": -1,
      "vendor": 24768
    },
    "Radiant Hat": {
      "ask": 650000,
      "bid": -1,
      "vendor": 30960
    },
    "Radiant Robe Bottoms": {
      "ask": 250000,
      "bid": -1,
      "vendor": 43344
    },
    "Radiant Robe Top": {
      "ask": 250000,
      "bid": -1,
      "vendor": 49536
    },
    "Rain Of Arrows": {
      "ask": 689996,
      "bid": 550001,
      "vendor": 1000
    },
    "Rainbow Boots": {
      "ask": 12000,
      "bid": -1,
      "vendor": 11988
    },
    "Rainbow Brush": {
      "ask": -1,
      "bid": 30000,
      "vendor": 20979
    },
    "Rainbow Buckler": {
      "ask": 49997,
      "bid": -1,
      "vendor": 17982
    },
    "Rainbow Bulwark": {
      "ask": -1,
      "bid": -1,
      "vendor": 35964
    },
    "Rainbow Cheese": {
      "ask": 333,
      "bid": 296,
      "vendor": 81
    },
    "Rainbow Chisel": {
      "ask": 149625,
      "bid": -1,
      "vendor": 20979
    },
    "Rainbow Enhancer": {
      "ask": 49870,
      "bid": 25000,
      "vendor": 20979
    },
    "Rainbow Gauntlets": {
      "ask": -1,
      "bid": -1,
      "vendor": 11988
    },
    "Rainbow Hammer": {
      "ask": -1,
      "bid": 25000,
      "vendor": 20979
    },
    "Rainbow Hatchet": {
      "ask": 75000,
      "bid": -1,
      "vendor": 20979
    },
    "Rainbow Helmet": {
      "ask": 42860,
      "bid": -1,
      "vendor": 14985
    },
    "Rainbow Mace": {
      "ask": 30000,
      "bid": -1,
      "vendor": 26973
    },
    "Rainbow Milk": {
      "ask": 31,
      "bid": 28,
      "vendor": 27
    },
    "Rainbow Needle": {
      "ask": 199999,
      "bid": -1,
      "vendor": 20979
    },
    "Rainbow Plate Body": {
      "ask": 49998,
      "bid": -1,
      "vendor": 23976
    },
    "Rainbow Plate Legs": {
      "ask": 60000,
      "bid": 22001,
      "vendor": 20979
    },
    "Rainbow Pot": {
      "ask": 55545,
      "bid": 23000,
      "vendor": 20979
    },
    "Rainbow Shears": {
      "ask": -1,
      "bid": 25000,
      "vendor": 20979
    },
    "Rainbow Spatula": {
      "ask": 49999,
      "bid": 25000,
      "vendor": 20979
    },
    "Rainbow Spear": {
      "ask": 54148,
      "bid": 20000,
      "vendor": 26973
    },
    "Rainbow Sword": {
      "ask": 43976,
      "bid": 22000,
      "vendor": 26973
    },
    "Ranged Coffee": {
      "ask": 619,
      "bid": 424,
      "vendor": 30
    },
    "Red Tea Leaf": {
      "ask": 450,
      "bid": 418,
      "vendor": 27
    },
    "Redwood Bow": {
      "ask": 49513,
      "bid": -1,
      "vendor": 35964
    },
    "Redwood Crossbow": {
      "ask": 55000,
      "bid": -1,
      "vendor": 26973
    },
    "Redwood Fire Staff": {
      "ask": 54863,
      "bid": -1,
      "vendor": 26973
    },
    "Redwood Log": {
      "ask": 69,
      "bid": 36,
      "vendor": 27
    },
    "Redwood Lumber": {
      "ask": 665,
      "bid": 350,
      "vendor": 81
    },
    "Redwood Nature Staff": {
      "ask": 55000,
      "bid": -1,
      "vendor": 26973
    },
    "Redwood Water Staff": {
      "ask": 55000,
      "bid": -1,
      "vendor": 26973
    },
    "Reptile Boots": {
      "ask": 6999,
      "bid": 2500,
      "vendor": 432
    },
    "Reptile Bracers": {
      "ask": 8999,
      "bid": -1,
      "vendor": 432
    },
    "Reptile Chaps": {
      "ask": 11999,
      "bid": -1,
      "vendor": 756
    },
    "Reptile Hide": {
      "ask": 32,
      "bid": 20,
      "vendor": 6
    },
    "Reptile Hood": {
      "ask": 17500,
      "bid": -1,
      "vendor": 540
    },
    "Reptile Leather": {
      "ask": 224,
      "bid": 181,
      "vendor": 18
    },
    "Reptile Tunic": {
      "ask": 6000,
      "bid": -1,
      "vendor": 864
    },
    "Robusta Coffee Bean": {
      "ask": 147,
      "bid": 76,
      "vendor": 8
    },
    "Rough Boots": {
      "ask": 4284,
      "bid": 1000,
      "vendor": 48
    },
    "Rough Bracers": {
      "ask": 21174,
      "bid": -1,
      "vendor": 48
    },
    "Rough Chaps": {
      "ask": 44795,
      "bid": 401,
      "vendor": 84
    },
    "Rough Hide": {
      "ask": 114,
      "bid": 68,
      "vendor": 2
    },
    "Rough Hood": {
      "ask": 6982,
      "bid": 60,
      "vendor": 60
    },
    "Rough Leather": {
      "ask": 235,
      "bid": 172,
      "vendor": 6
    },
    "Rough Tunic": {
      "ask": 8999,
      "bid": -1,
      "vendor": 96
    },
    "Scratch": {
      "ask": 1700,
      "bid": 1203,
      "vendor": 1000
    },
    "Silk Boots": {
      "ask": 98587,
      "bid": -1,
      "vendor": 7200
    },
    "Silk Fabric": {
      "ask": 616,
      "bid": 353,
      "vendor": 73
    },
    "Silk Gloves": {
      "ask": 148336,
      "bid": -1,
      "vendor": 7200
    },
    "Silk Hat": {
      "ask": 48997,
      "bid": 10000,
      "vendor": 9000
    },
    "Silk Robe Bottoms": {
      "ask": 155958,
      "bid": -1,
      "vendor": 12600
    },
    "Silk Robe Top": {
      "ask": 88997,
      "bid": -1,
      "vendor": 14400
    },
    "Smack": {
      "ask": 1800,
      "bid": 529,
      "vendor": 1000
    },
    "Small Pouch": {
      "ask": 33999,
      "bid": 3,
      "vendor": 5000
    },
    "Snail Shell": {
      "ask": 20000,
      "bid": 3121,
      "vendor": 1500
    },
    "Snail Shell Helmet": {
      "ask": 199999,
      "bid": 6385,
      "vendor": 6000
    },
    "Snake Fang": {
      "ask": 1800,
      "bid": 300,
      "vendor": 100
    },
    "Snake Fang Dirk": {
      "ask": 8888,
      "bid": 3000,
      "vendor": 2000
    },
    "Sorcerer Boots": {
      "ask": 1500000,
      "bid": 650000,
      "vendor": 50000
    },
    "Sorcerer Essence": {
      "ask": 475,
      "bid": 276,
      "vendor": 36
    },
    "Sorcerer's Sole": {
      "ask": 474989,
      "bid": 40002,
      "vendor": 3000
    },
    "Spaceberry": {
      "ask": 186,
      "bid": 95,
      "vendor": 27
    },
    "Spaceberry Cake": {
      "ask": 840,
      "bid": 780,
      "vendor": 75
    },
    "Spaceberry Donut": {
      "ask": 796,
      "bid": 751,
      "vendor": 75
    },
    "Spacia Coffee Bean": {
      "ask": 408,
      "bid": 400,
      "vendor": 54
    },
    "Spike Shell": {
      "ask": 179999,
      "bid": 50401,
      "vendor": 1000
    },
    "Stalactite Shard": {
      "ask": 1999999,
      "bid": 400001,
      "vendor": 10000
    },
    "Stalactite Spear": {
      "ask": 36000000,
      "bid": 1000,
      "vendor": 400000
    },
    "Stamina Coffee": {
      "ask": 293,
      "bid": 138,
      "vendor": 10
    },
    "Star Fruit": {
      "ask": 208,
      "bid": 118,
      "vendor": 27
    },
    "Star Fruit Gummy": {
      "ask": 735,
      "bid": 614,
      "vendor": 75
    },
    "Star Fruit Yogurt": {
      "ask": 850,
      "bid": 754,
      "vendor": 75
    },
    "Strawberry": {
      "ask": 59,
      "bid": 52,
      "vendor": 6
    },
    "Strawberry Cake": {
      "ask": 244,
      "bid": 118,
      "vendor": 30
    },
    "Strawberry Donut": {
      "ask": 227,
      "bid": 101,
      "vendor": 30
    },
    "Stunning Blow": {
      "ask": 307987,
      "bid": 150008,
      "vendor": 1000
    },
    "Sugar": {
      "ask": 3,
      "bid": 2,
      "vendor": 1
    },
    "Super Attack Coffee": {
      "ask": 490,
      "bid": 250,
      "vendor": 50
    },
    "Super Brewing Tea": {
      "ask": 664,
      "bid": 103,
      "vendor": 50
    },
    "Super Cheesesmithing Tea": {
      "ask": 1080,
      "bid": 531,
      "vendor": 75
    },
    "Super Cooking Tea": {
      "ask": 597,
      "bid": 303,
      "vendor": 50
    },
    "Super Crafting Tea": {
      "ask": 1988,
      "bid": 1000,
      "vendor": 75
    },
    "Super Defense Coffee": {
      "ask": 906,
      "bid": 651,
      "vendor": 50
    },
    "Super Enhancing Tea": {
      "ask": 1187,
      "bid": 308,
      "vendor": 50
    },
    "Super Foraging Tea": {
      "ask": 4999,
      "bid": 201,
      "vendor": 40
    },
    "Super Intelligence Coffee": {
      "ask": 1200,
      "bid": 513,
      "vendor": 40
    },
    "Super Magic Coffee": {
      "ask": 3348,
      "bid": 1343,
      "vendor": 75
    },
    "Super Milking Tea": {
      "ask": 499,
      "bid": 301,
      "vendor": 40
    },
    "Super Power Coffee": {
      "ask": 1106,
      "bid": 1003,
      "vendor": 75
    },
    "Super Ranged Coffee": {
      "ask": 970,
      "bid": 860,
      "vendor": 75
    },
    "Super Stamina Coffee": {
      "ask": 800,
      "bid": 455,
      "vendor": 40
    },
    "Super Tailoring Tea": {
      "ask": 1498,
      "bid": 1005,
      "vendor": 75
    },
    "Super Woodcutting Tea": {
      "ask": 975,
      "bid": 250,
      "vendor": 40
    },
    "Swamp Essence": {
      "ask": 13,
      "bid": 10,
      "vendor": 8
    },
    "Sweep": {
      "ask": 20505,
      "bid": 11069,
      "vendor": 1000
    },
    "Swiftness Coffee": {
      "ask": 940,
      "bid": 824,
      "vendor": 50
    },
    "Tailoring Tea": {
      "ask": 933,
      "bid": 404,
      "vendor": 30
    },
    "Tome Of Healing": {
      "ask": 12496,
      "bid": 10043,
      "vendor": 10000
    },
    "Tome Of The Elements": {
      "ask": 3649988,
      "bid": 1000001,
      "vendor": 100000
    },
    "Toughness": {
      "ask": 34628,
      "bid": 20251,
      "vendor": 1000
    },
    "Toxic Pollen": {
      "ask": 9979998,
      "bid": 550016,
      "vendor": 1000
    },
    "Turtle Shell": {
      "ask": 196701,
      "bid": 2941,
      "vendor": 1500
    },
    "Turtle Shell Body": {
      "ask": 29000,
      "bid": -1,
      "vendor": 9000
    },
    "Turtle Shell Legs": {
      "ask": 38000,
      "bid": -1,
      "vendor": 6000
    },
    "Twilight Essence": {
      "ask": 366,
      "bid": 232,
      "vendor": 108
    },
    "Umbral Boots": {
      "ask": 264715,
      "bid": -1,
      "vendor": 24768
    },
    "Umbral Bracers": {
      "ask": 379997,
      "bid": -1,
      "vendor": 24768
    },
    "Umbral Chaps": {
      "ask": 433439,
      "bid": -1,
      "vendor": 43344
    },
    "Umbral Hide": {
      "ask": 758,
      "bid": 432,
      "vendor": 48
    },
    "Umbral Hood": {
      "ask": 379999,
      "bid": -1,
      "vendor": 30960
    },
    "Umbral Leather": {
      "ask": 9999,
      "bid": 150,
      "vendor": 144
    },
    "Umbral Tunic": {
      "ask": 499998,
      "bid": -1,
      "vendor": 49536
    },
    "Vampire Fang": {
      "ask": 1249979,
      "bid": 639457,
      "vendor": 10000
    },
    "Vampire Fang Dirk": {
      "ask": -1,
      "bid": 1000000,
      "vendor": 400000
    },
    "Vampirism": {
      "ask": 749848,
      "bid": 500019,
      "vendor": 1000
    },
    "Verdant Boots": {
      "ask": 497,
      "bid": -1,
      "vendor": 240
    },
    "Verdant Brush": {
      "ask": -1,
      "bid": 750,
      "vendor": 420
    },
    "Verdant Buckler": {
      "ask": 1000,
      "bid": 420,
      "vendor": 360
    },
    "Verdant Bulwark": {
      "ask": 3151,
      "bid": 1201,
      "vendor": 720
    },
    "Verdant Cheese": {
      "ask": 369,
      "bid": 245,
      "vendor": 12
    },
    "Verdant Chisel": {
      "ask": 10000,
      "bid": -1,
      "vendor": 420
    },
    "Verdant Enhancer": {
      "ask": 10000,
      "bid": 1000,
      "vendor": 420
    },
    "Verdant Gauntlets": {
      "ask": 7581,
      "bid": 383,
      "vendor": 240
    },
    "Verdant Hammer": {
      "ask": -1,
      "bid": 364,
      "vendor": 420
    },
    "Verdant Hatchet": {
      "ask": 25000,
      "bid": -1,
      "vendor": 420
    },
    "Verdant Helmet": {
      "ask": 14999,
      "bid": 803,
      "vendor": 300
    },
    "Verdant Mace": {
      "ask": 3000,
      "bid": 500,
      "vendor": 540
    },
    "Verdant Milk": {
      "ask": 63,
      "bid": 41,
      "vendor": 4
    },
    "Verdant Needle": {
      "ask": 15000,
      "bid": -1,
      "vendor": 420
    },
    "Verdant Plate Body": {
      "ask": 11970,
      "bid": 606,
      "vendor": 480
    },
    "Verdant Plate Legs": {
      "ask": 3000,
      "bid": 440,
      "vendor": 420
    },
    "Verdant Pot": {
      "ask": 11000,
      "bid": 445,
      "vendor": 420
    },
    "Verdant Shears": {
      "ask": 9000,
      "bid": 430,
      "vendor": 420
    },
    "Verdant Spatula": {
      "ask": -1,
      "bid": 3000,
      "vendor": 420
    },
    "Verdant Spear": {
      "ask": 11999,
      "bid": 250,
      "vendor": 540
    },
    "Verdant Sword": {
      "ask": 13000,
      "bid": 500,
      "vendor": 540
    },
    "Vision Helmet": {
      "ask": 150935,
      "bid": 20000,
      "vendor": 20000
    },
    "Vision Shield": {
      "ask": 279998,
      "bid": 71840,
      "vendor": 20000
    },
    "Water Strike": {
      "ask": 15000,
      "bid": 2728,
      "vendor": 1000
    },
    "Werewolf Claw": {
      "ask": 482529,
      "bid": 315012,
      "vendor": 10000
    },
    "Werewolf Slasher": {
      "ask": 10000000,
      "bid": 1001,
      "vendor": 400000
    },
    "Wheat": {
      "ask": 32,
      "bid": 15,
      "vendor": 1
    },
    "Wisdom Coffee": {
      "ask": 1599,
      "bid": 1028,
      "vendor": 30
    },
    "Wisdom Tea": {
      "ask": 995,
      "bid": 726,
      "vendor": 30
    },
    "Woodcutting Tea": {
      "ask": 100000,
      "bid": 125,
      "vendor": 10
    },
    "Wooden Bow": {
      "ask": 6472,
      "bid": -1,
      "vendor": 144
    },
    "Wooden Crossbow": {
      "ask": 2185,
      "bid": -1,
      "vendor": 108
    },
    "Wooden Fire Staff": {
      "ask": 25000,
      "bid": -1,
      "vendor": 108
    },
    "Wooden Nature Staff": {
      "ask": 5000,
      "bid": -1,
      "vendor": 108
    },
    "Wooden Water Staff": {
      "ask": 19000,
      "bid": -1,
      "vendor": 108
    },
    "Yogurt": {
      "ask": 25,
      "bid": 6,
      "vendor": 5
    }
  },
  "time": 1669512603.2303126
}