{
  "market": {
    "Apple": {
      "ask": 16,
      "bid": 6,
      "vendor": 2
    },
    "Apple Gummy": {
      "ask": 22,
      "bid": 10,
      "vendor": 10
    },
    "Apple Yogurt": {
      "ask": 50,
      "bid": 28,
      "vendor": 10
    },
    "Aqua Essence": {
      "ask": 17,
      "bid": 15,
      "vendor": 16
    },
    "Arabica Coffee Bean": {
      "ask": 81,
      "bid": 35,
      "vendor": 4
    },
    "Artisan Tea": {
      "ask": 800,
      "bid": 80,
      "vendor": 75
    },
    "Attack Coffee": {
      "ask": 170,
      "bid": 43,
      "vendor": 20
    },
    "Azure Boots": {
      "ask": 27777,
      "bid": 1055,
      "vendor": 864
    },
    "Azure Brush": {
      "ask": 24888,
      "bid": 1450,
      "vendor": 1080
    },
    "Azure Buckler": {
      "ask": 24875,
      "bid": 1650,
      "vendor": 1296
    },
    "Azure Bulwark": {
      "ask": 29000,
      "bid": 2332,
      "vendor": 2160
    },
    "Azure Cheese": {
      "ask": 143,
      "bid": 126,
      "vendor": 24
    },
    "Azure Enhancer": {
      "ask": 18600,
      "bid": 1644,
      "vendor": 1080
    },
    "Azure Gauntlets": {
      "ask": 30000,
      "bid": 3630,
      "vendor": 864
    },
    "Azure Hammer": {
      "ask": 8132,
      "bid": 1525,
      "vendor": 1080
    },
    "Azure Helmet": {
      "ask": 30000,
      "bid": 5050,
      "vendor": 1080
    },
    "Azure Mace": {
      "ask": 13992,
      "bid": 3000,
      "vendor": 1296
    },
    "Azure Milk": {
      "ask": 40,
      "bid": 33,
      "vendor": 8
    },
    "Azure Plate Body": {
      "ask": 30000,
      "bid": 2255,
      "vendor": 1944
    },
    "Azure Plate Legs": {
      "ask": 24758,
      "bid": 5050,
      "vendor": 1512
    },
    "Azure Pot": {
      "ask": 12986,
      "bid": 1200,
      "vendor": 1080
    },
    "Azure Shears": {
      "ask": 4736,
      "bid": 1729,
      "vendor": 1080
    },
    "Azure Spatula": {
      "ask": 14000,
      "bid": 1730,
      "vendor": 1080
    },
    "Azure Spear": {
      "ask": 24862,
      "bid": 3000,
      "vendor": 1296
    },
    "Azure Sword": {
      "ask": 11878,
      "bid": 4641,
      "vendor": 1296
    },
    "Bear Essence": {
      "ask": 55,
      "bid": 54,
      "vendor": 54
    },
    "Berserk": {
      "ask": 109997,
      "bid": 90000,
      "vendor": 1000
    },
    "Black Bear Fluff": {
      "ask": 280869,
      "bid": 100017,
      "vendor": 3000
    },
    "Black Bear Shoes": {
      "ask": -1,
      "bid": 300000,
      "vendor": 60000
    },
    "Black Tea Leaf": {
      "ask": 124,
      "bid": 70,
      "vendor": 8
    },
    "Blackberry": {
      "ask": 20,
      "bid": 14,
      "vendor": 4
    },
    "Blackberry Cake": {
      "ask": 147,
      "bid": 92,
      "vendor": 20
    },
    "Blackberry Donut": {
      "ask": 97,
      "bid": 31,
      "vendor": 20
    },
    "Blessed Tea": {
      "ask": 1703,
      "bid": 1311,
      "vendor": 75
    },
    "Blueberry": {
      "ask": 14,
      "bid": 11,
      "vendor": 2
    },
    "Blueberry Cake": {
      "ask": 99,
      "bid": 41,
      "vendor": 10
    },
    "Blueberry Donut": {
      "ask": 44,
      "bid": 13,
      "vendor": 10
    },
    "Brewing Tea": {
      "ask": 335,
      "bid": 46,
      "vendor": 20
    },
    "Burble Boots": {
      "ask": 12000,
      "bid": 3175,
      "vendor": 2160
    },
    "Burble Brush": {
      "ask": 11946,
      "bid": 3841,
      "vendor": 2700
    },
    "Burble Buckler": {
      "ask": 34872,
      "bid": 4035,
      "vendor": 3240
    },
    "Burble Bulwark": {
      "ask": 7500,
      "bid": 5746,
      "vendor": 5400
    },
    "Burble Cheese": {
      "ask": 165,
      "bid": 129,
      "vendor": 36
    },
    "Burble Enhancer": {
      "ask": 40000,
      "bid": 3026,
      "vendor": 2700
    },
    "Burble Gauntlets": {
      "ask": 13690,
      "bid": 3025,
      "vendor": 2160
    },
    "Burble Hammer": {
      "ask": 13537,
      "bid": 3480,
      "vendor": 2700
    },
    "Burble Helmet": {
      "ask": 33762,
      "bid": 5050,
      "vendor": 2700
    },
    "Burble Mace": {
      "ask": 31463,
      "bid": 6040,
      "vendor": 3240
    },
    "Burble Milk": {
      "ask": 32,
      "bid": 31,
      "vendor": 12
    },
    "Burble Plate Body": {
      "ask": 15000,
      "bid": 8000,
      "vendor": 4860
    },
    "Burble Plate Legs": {
      "ask": 39775,
      "bid": 4567,
      "vendor": 3780
    },
    "Burble Pot": {
      "ask": 9899,
      "bid": 3236,
      "vendor": 2700
    },
    "Burble Shears": {
      "ask": 40000,
      "bid": 3152,
      "vendor": 2700
    },
    "Burble Spatula": {
      "ask": 11498,
      "bid": 3130,
      "vendor": 2700
    },
    "Burble Spear": {
      "ask": 18888,
      "bid": 3504,
      "vendor": 3240
    },
    "Burble Sword": {
      "ask": 34437,
      "bid": 3461,
      "vendor": 3240
    },
    "Burble Tea Leaf": {
      "ask": 349,
      "bid": 327,
      "vendor": 12
    },
    "Cheese": {
      "ask": 90,
      "bid": 70,
      "vendor": 6
    },
    "Cheese Boots": {
      "ask": -1,
      "bid": 136,
      "vendor": 48
    },
    "Cheese Brush": {
      "ask": 950,
      "bid": 170,
      "vendor": 60
    },
    "Cheese Buckler": {
      "ask": 700,
      "bid": 222,
      "vendor": 72
    },
    "Cheese Bulwark": {
      "ask": 200,
      "bid": 173,
      "vendor": 120
    },
    "Cheese Enhancer": {
      "ask": 1288,
      "bid": 301,
      "vendor": 60
    },
    "Cheese Gauntlets": {
      "ask": -1,
      "bid": 138,
      "vendor": 48
    },
    "Cheese Hammer": {
      "ask": 500,
      "bid": 165,
      "vendor": 60
    },
    "Cheese Helmet": {
      "ask": 1985,
      "bid": 256,
      "vendor": 60
    },
    "Cheese Mace": {
      "ask": 566,
      "bid": 172,
      "vendor": 72
    },
    "Cheese Plate Body": {
      "ask": 2586,
      "bid": 321,
      "vendor": 108
    },
    "Cheese Plate Legs": {
      "ask": -1,
      "bid": 308,
      "vendor": 84
    },
    "Cheese Pot": {
      "ask": 666,
      "bid": 163,
      "vendor": 60
    },
    "Cheese Shears": {
      "ask": 4061,
      "bid": 165,
      "vendor": 60
    },
    "Cheese Spatula": {
      "ask": 420,
      "bid": 161,
      "vendor": 60
    },
    "Cheese Spear": {
      "ask": 9449,
      "bid": 175,
      "vendor": 72
    },
    "Cheese Sword": {
      "ask": 4640,
      "bid": 179,
      "vendor": 72
    },
    "Cheesesmithing Tea": {
      "ask": 545,
      "bid": 35,
      "vendor": 30
    },
    "Cleave": {
      "ask": 74999,
      "bid": 30001,
      "vendor": 1000
    },
    "Coin": {
      "ask": -1,
      "bid": -1,
      "vendor": 0
    },
    "Cooking Tea": {
      "ask": 375,
      "bid": 200,
      "vendor": 20
    },
    "Crab Pincer": {
      "ask": 15498,
      "bid": 12301,
      "vendor": 1500
    },
    "Crimson Boots": {
      "ask": 19993,
      "bid": 5525,
      "vendor": 5184
    },
    "Crimson Brush": {
      "ask": 25000,
      "bid": 6827,
      "vendor": 6480
    },
    "Crimson Buckler": {
      "ask": 40000,
      "bid": 15000,
      "vendor": 7776
    },
    "Crimson Bulwark": {
      "ask": 27431,
      "bid": 13620,
      "vendor": 12960
    },
    "Crimson Cheese": {
      "ask": 115,
      "bid": 114,
      "vendor": 54
    },
    "Crimson Enhancer": {
      "ask": 25332,
      "bid": 7058,
      "vendor": 6480
    },
    "Crimson Gauntlets": {
      "ask": 24996,
      "bid": 5613,
      "vendor": 5184
    },
    "Crimson Hammer": {
      "ask": 19000,
      "bid": 6850,
      "vendor": 6480
    },
    "Crimson Helmet": {
      "ask": 42750,
      "bid": 6775,
      "vendor": 6480
    },
    "Crimson Mace": {
      "ask": 24636,
      "bid": 8220,
      "vendor": 7776
    },
    "Crimson Milk": {
      "ask": 21,
      "bid": 20,
      "vendor": 18
    },
    "Crimson Plate Body": {
      "ask": 28543,
      "bid": 14666,
      "vendor": 11664
    },
    "Crimson Plate Legs": {
      "ask": 19886,
      "bid": 9605,
      "vendor": 9072
    },
    "Crimson Pot": {
      "ask": 19898,
      "bid": 6826,
      "vendor": 6480
    },
    "Crimson Shears": {
      "ask": 15998,
      "bid": 10000,
      "vendor": 6480
    },
    "Crimson Spatula": {
      "ask": 50000,
      "bid": 6822,
      "vendor": 6480
    },
    "Crimson Spear": {
      "ask": 25252,
      "bid": 8070,
      "vendor": 7776
    },
    "Crimson Sword": {
      "ask": 20000,
      "bid": 8245,
      "vendor": 7776
    },
    "Cupcake": {
      "ask": 32,
      "bid": 16,
      "vendor": 5
    },
    "Defense Coffee": {
      "ask": 210,
      "bid": 81,
      "vendor": 20
    },
    "Donut": {
      "ask": 36,
      "bid": 11,
      "vendor": 5
    },
    "Dragon Fruit": {
      "ask": 47,
      "bid": 33,
      "vendor": 14
    },
    "Dragon Fruit Gummy": {
      "ask": 258,
      "bid": 105,
      "vendor": 50
    },
    "Dragon Fruit Yogurt": {
      "ask": 290,
      "bid": 259,
      "vendor": 50
    },
    "Efficiency Tea": {
      "ask": 899,
      "bid": 701,
      "vendor": 50
    },
    "Egg": {
      "ask": 20,
      "bid": 14,
      "vendor": 1
    },
    "Emp Tea Leaf": {
      "ask": 116,
      "bid": 96,
      "vendor": 54
    },
    "Enhancing Tea": {
      "ask": 279,
      "bid": 31,
      "vendor": 20
    },
    "Excelsa Coffee Bean": {
      "ask": 32,
      "bid": 24,
      "vendor": 18
    },
    "Eyessence": {
      "ask": 42,
      "bid": 37,
      "vendor": 36
    },
    "Fermenting Tea": {
      "ask": 487,
      "bid": 356,
      "vendor": 40
    },
    "Fieriosa Coffee Bean": {
      "ask": 118,
      "bid": 70,
      "vendor": 27
    },
    "Foraging Tea": {
      "ask": 495,
      "bid": 200,
      "vendor": 10
    },
    "Frenzy": {
      "ask": 185999,
      "bid": 120000,
      "vendor": 1000
    },
    "Gathering Tea": {
      "ask": 588,
      "bid": 302,
      "vendor": 10
    },
    "Gator Vest": {
      "ask": 23018,
      "bid": 10556,
      "vendor": 5000
    },
    "Giant Pouch": {
      "ask": -1,
      "bid": 5000001,
      "vendor": 5000000
    },
    "Gobo Essence": {
      "ask": 30,
      "bid": 27,
      "vendor": 24
    },
    "Gobo Slasher": {
      "ask": 31995,
      "bid": 21111,
      "vendor": 20000
    },
    "Gobo Smasher": {
      "ask": 32500,
      "bid": 27800,
      "vendor": 20000
    },
    "Gobo Stabber": {
      "ask": 24000,
      "bid": 20555,
      "vendor": 20000
    },
    "Goggles": {
      "ask": 400000,
      "bid": 300009,
      "vendor": 10000
    },
    "Gourmet Tea": {
      "ask": 519,
      "bid": 317,
      "vendor": 20
    },
    "Green Tea Leaf": {
      "ask": 76,
      "bid": 67,
      "vendor": 4
    },
    "Grizzly Bear Fluff": {
      "ask": 284050,
      "bid": 202006,
      "vendor": 3000
    },
    "Grizzly Bear Shoes": {
      "ask": 2750000,
      "bid": 1,
      "vendor": 60000
    },
    "Gummy": {
      "ask": 100,
      "bid": 13,
      "vendor": 5
    },
    "Holy Boots": {
      "ask": 38499,
      "bid": 2,
      "vendor": 35640
    },
    "Holy Brush": {
      "ask": 62000,
      "bid": 56000,
      "vendor": 44550
    },
    "Holy Buckler": {
      "ask": 89980,
      "bid": -1,
      "vendor": 53460
    },
    "Holy Bulwark": {
      "ask": 147997,
      "bid": -1,
      "vendor": 89100
    },
    "Holy Cheese": {
      "ask": 424,
      "bid": 410,
      "vendor": 162
    },
    "Holy Enhancer": {
      "ask": 61979,
      "bid": 45678,
      "vendor": 44550
    },
    "Holy Gauntlets": {
      "ask": 36498,
      "bid": -1,
      "vendor": 35640
    },
    "Holy Hammer": {
      "ask": 63500,
      "bid": 51,
      "vendor": 44550
    },
    "Holy Helmet": {
      "ask": 70751,
      "bid": -1,
      "vendor": 44550
    },
    "Holy Mace": {
      "ask": 76635,
      "bid": -1,
      "vendor": 53460
    },
    "Holy Milk": {
      "ask": 87,
      "bid": 76,
      "vendor": 54
    },
    "Holy Plate Body": {
      "ask": 134000,
      "bid": -1,
      "vendor": 80190
    },
    "Holy Plate Legs": {
      "ask": 99500,
      "bid": -1,
      "vendor": 62370
    },
    "Holy Pot": {
      "ask": 69998,
      "bid": 45678,
      "vendor": 44550
    },
    "Holy Shears": {
      "ask": 74994,
      "bid": 45678,
      "vendor": 44550
    },
    "Holy Spatula": {
      "ask": 89496,
      "bid": 45678,
      "vendor": 44550
    },
    "Holy Spear": {
      "ask": 70000,
      "bid": -1,
      "vendor": 53460
    },
    "Holy Sword": {
      "ask": 77767,
      "bid": 1,
      "vendor": 53460
    },
    "Intelligence Coffee": {
      "ask": 389,
      "bid": 129,
      "vendor": 10
    },
    "Large Pouch": {
      "ask": -1,
      "bid": 1850000,
      "vendor": 500000
    },
    "Liberica Coffee Bean": {
      "ask": 68,
      "bid": 16,
      "vendor": 12
    },
    "Lucky Coffee": {
      "ask": 100,
      "bid": 65,
      "vendor": 40
    },
    "Magnifying Glass": {
      "ask": 504769,
      "bid": 325531,
      "vendor": 10000
    },
    "Maim": {
      "ask": 2200000,
      "bid": 1550000,
      "vendor": 1000
    },
    "Marsberry": {
      "ask": 24,
      "bid": 21,
      "vendor": 14
    },
    "Marsberry Cake": {
      "ask": 358,
      "bid": 325,
      "vendor": 50
    },
    "Marsberry Donut": {
      "ask": -1,
      "bid": 130,
      "vendor": 50
    },
    "Medium Pouch": {
      "ask": 165000,
      "bid": 70001,
      "vendor": 50000
    },
    "Milk": {
      "ask": 20,
      "bid": 19,
      "vendor": 2
    },
    "Milking Tea": {
      "ask": 190,
      "bid": 24,
      "vendor": 10
    },
    "Mooberry": {
      "ask": 26,
      "bid": 14,
      "vendor": 9
    },
    "Mooberry Cake": {
      "ask": 250,
      "bid": 205,
      "vendor": 40
    },
    "Mooberry Donut": {
      "ask": 400,
      "bid": 120,
      "vendor": 40
    },
    "Moolong Tea Leaf": {
      "ask": 55,
      "bid": 29,
      "vendor": 18
    },
    "Orange": {
      "ask": 8,
      "bid": 7,
      "vendor": 4
    },
    "Orange Gummy": {
      "ask": 34,
      "bid": -1,
      "vendor": 20
    },
    "Orange Yogurt": {
      "ask": 94,
      "bid": 55,
      "vendor": 20
    },
    "Panda Fluff": {
      "ask": 472608,
      "bid": 400002,
      "vendor": 3000
    },
    "Panda Gloves": {
      "ask": -1,
      "bid": 1000000,
      "vendor": 60000
    },
    "Peach": {
      "ask": 35,
      "bid": 24,
      "vendor": 9
    },
    "Peach Gummy": {
      "ask": 94,
      "bid": 45,
      "vendor": 40
    },
    "Peach Yogurt": {
      "ask": 181,
      "bid": 72,
      "vendor": 40
    },
    "Pierce": {
      "ask": 33799,
      "bid": 18023,
      "vendor": 1000
    },
    "Pincer Gloves": {
      "ask": 39932,
      "bid": 24444,
      "vendor": 6000
    },
    "Plum": {
      "ask": 11,
      "bid": 8,
      "vendor": 6
    },
    "Plum Gummy": {
      "ask": 85,
      "bid": -1,
      "vendor": 30
    },
    "Plum Yogurt": {
      "ask": 149,
      "bid": 53,
      "vendor": 30
    },
    "Poke": {
      "ask": 21000,
      "bid": 2126,
      "vendor": 1000
    },
    "Polar Bear Fluff": {
      "ask": 272914,
      "bid": 175001,
      "vendor": 3000
    },
    "Polar Bear Shoes": {
      "ask": -1,
      "bid": 70000,
      "vendor": 60000
    },
    "Power Coffee": {
      "ask": 92,
      "bid": 60,
      "vendor": 30
    },
    "Precision": {
      "ask": 17998,
      "bid": 1702,
      "vendor": 1000
    },
    "Rainbow Boots": {
      "ask": 25000,
      "bid": 12400,
      "vendor": 11988
    },
    "Rainbow Brush": {
      "ask": 50000,
      "bid": 20600,
      "vendor": 14985
    },
    "Rainbow Buckler": {
      "ask": -1,
      "bid": -1,
      "vendor": 17982
    },
    "Rainbow Bulwark": {
      "ask": 39257,
      "bid": -1,
      "vendor": 29970
    },
    "Rainbow Cheese": {
      "ask": 219,
      "bid": 192,
      "vendor": 81
    },
    "Rainbow Enhancer": {
      "ask": 50000,
      "bid": 19000,
      "vendor": 14985
    },
    "Rainbow Gauntlets": {
      "ask": 38000,
      "bid": -1,
      "vendor": 11988
    },
    "Rainbow Hammer": {
      "ask": 26571,
      "bid": 18000,
      "vendor": 14985
    },
    "Rainbow Helmet": {
      "ask": 49999,
      "bid": -1,
      "vendor": 14985
    },
    "Rainbow Mace": {
      "ask": 35917,
      "bid": 25500,
      "vendor": 17982
    },
    "Rainbow Milk": {
      "ask": 38,
      "bid": 32,
      "vendor": 27
    },
    "Rainbow Plate Body": {
      "ask": 69000,
      "bid": -1,
      "vendor": 26973
    },
    "Rainbow Plate Legs": {
      "ask": 54966,
      "bid": 22501,
      "vendor": 20979
    },
    "Rainbow Pot": {
      "ask": 49993,
      "bid": 21000,
      "vendor": 14985
    },
    "Rainbow Shears": {
      "ask": 50000,
      "bid": 20000,
      "vendor": 14985
    },
    "Rainbow Spatula": {
      "ask": 49999,
      "bid": 20000,
      "vendor": 14985
    },
    "Rainbow Spear": {
      "ask": 34163,
      "bid": 1,
      "vendor": 17982
    },
    "Rainbow Sword": {
      "ask": 34980,
      "bid": 25000,
      "vendor": 17982
    },
    "Red Tea Leaf": {
      "ask": 246,
      "bid": 201,
      "vendor": 27
    },
    "Robusta Coffee Bean": {
      "ask": 93,
      "bid": 42,
      "vendor": 8
    },
    "Scratch": {
      "ask": 27000,
      "bid": 4109,
      "vendor": 1000
    },
    "Smack": {
      "ask": 17500,
      "bid": 3001,
      "vendor": 1000
    },
    "Small Pouch": {
      "ask": 5250,
      "bid": 3,
      "vendor": 5000
    },
    "Snail Shell": {
      "ask": 7125,
      "bid": 2600,
      "vendor": 1500
    },
    "Snail Shell Helmet": {
      "ask": 6296,
      "bid": 5000,
      "vendor": 6000
    },
    "Snake Fang": {
      "ask": 785,
      "bid": 526,
      "vendor": 100
    },
    "Snake Fang Dirk": {
      "ask": 7999,
      "bid": 2458,
      "vendor": 2000
    },
    "Spaceberry": {
      "ask": 57,
      "bid": 36,
      "vendor": 27
    },
    "Spaceberry Cake": {
      "ask": 422,
      "bid": 386,
      "vendor": 75
    },
    "Spaceberry Donut": {
      "ask": -1,
      "bid": -1,
      "vendor": 75
    },
    "Spacia Coffee Bean": {
      "ask": 198,
      "bid": 133,
      "vendor": 54
    },
    "Stamina Coffee": {
      "ask": 980,
      "bid": 111,
      "vendor": 10
    },
    "Star Fruit": {
      "ask": 88,
      "bid": 50,
      "vendor": 27
    },
    "Star Fruit Gummy": {
      "ask": -1,
      "bid": 120,
      "vendor": 75
    },
    "Star Fruit Yogurt": {
      "ask": 385,
      "bid": 350,
      "vendor": 75
    },
    "Strawberry": {
      "ask": 21,
      "bid": 18,
      "vendor": 6
    },
    "Strawberry Cake": {
      "ask": 204,
      "bid": 130,
      "vendor": 30
    },
    "Strawberry Donut": {
      "ask": 230,
      "bid": 35,
      "vendor": 30
    },
    "Sugar": {
      "ask": 7,
      "bid": 5,
      "vendor": 1
    },
    "Super Attack Coffee": {
      "ask": 376,
      "bid": 276,
      "vendor": 50
    },
    "Super Brewing Tea": {
      "ask": 999,
      "bid": 55,
      "vendor": 50
    },
    "Super Cheesesmithing Tea": {
      "ask": 998,
      "bid": 800,
      "vendor": 75
    },
    "Super Cooking Tea": {
      "ask": 750,
      "bid": 56,
      "vendor": 50
    },
    "Super Defense Coffee": {
      "ask": 300,
      "bid": 250,
      "vendor": 50
    },
    "Super Enhancing Tea": {
      "ask": 980,
      "bid": 710,
      "vendor": 50
    },
    "Super Foraging Tea": {
      "ask": 700,
      "bid": 45,
      "vendor": 40
    },
    "Super Intelligence Coffee": {
      "ask": 494,
      "bid": 475,
      "vendor": 40
    },
    "Super Milking Tea": {
      "ask": 645,
      "bid": 310,
      "vendor": 40
    },
    "Super Power Coffee": {
      "ask": 495,
      "bid": 401,
      "vendor": 75
    },
    "Super Stamina Coffee": {
      "ask": 315,
      "bid": 200,
      "vendor": 40
    },
    "Swamp Essence": {
      "ask": 20,
      "bid": 13,
      "vendor": 8
    },
    "Sweep": {
      "ask": 94516,
      "bid": 70000,
      "vendor": 1000
    },
    "Swiftness Coffee": {
      "ask": 550,
      "bid": 401,
      "vendor": 50
    },
    "Toughness": {
      "ask": 14999,
      "bid": 9001,
      "vendor": 1000
    },
    "Turtle Shell": {
      "ask": 50000,
      "bid": 20000,
      "vendor": 1500
    },
    "Turtle Shell Body": {
      "ask": 43555,
      "bid": -1,
      "vendor": 9000
    },
    "Turtle Shell Legs": {
      "ask": 50000,
      "bid": -1,
      "vendor": 6000
    },
    "Twilight Essence": {
      "ask": 349,
      "bid": 150,
      "vendor": 108
    },
    "Vampire Fang": {
      "ask": -1,
      "bid": 1200005,
      "vendor": 10000
    },
    "Vampire Fang Dirk": {
      "ask": -1,
      "bid": 1337,
      "vendor": 400000
    },
    "Vampirism": {
      "ask": 992515,
      "bid": 250001,
      "vendor": 1000
    },
    "Verdant Boots": {
      "ask": 4740,
      "bid": 295,
      "vendor": 240
    },
    "Verdant Brush": {
      "ask": 2999,
      "bid": 342,
      "vendor": 300
    },
    "Verdant Buckler": {
      "ask": 4208,
      "bid": 420,
      "vendor": 360
    },
    "Verdant Bulwark": {
      "ask": 18888,
      "bid": 679,
      "vendor": 600
    },
    "Verdant Cheese": {
      "ask": 128,
      "bid": 104,
      "vendor": 12
    },
    "Verdant Enhancer": {
      "ask": 1000,
      "bid": 350,
      "vendor": 300
    },
    "Verdant Gauntlets": {
      "ask": 900,
      "bid": 380,
      "vendor": 240
    },
    "Verdant Hammer": {
      "ask": -1,
      "bid": 315,
      "vendor": 300
    },
    "Verdant Helmet": {
      "ask": 19888,
      "bid": 730,
      "vendor": 300
    },
    "Verdant Mace": {
      "ask": 4002,
      "bid": 420,
      "vendor": 360
    },
    "Verdant Milk": {
      "ask": 25,
      "bid": 14,
      "vendor": 4
    },
    "Verdant Plate Body": {
      "ask": 29880,
      "bid": 630,
      "vendor": 540
    },
    "Verdant Plate Legs": {
      "ask": 15288,
      "bid": 450,
      "vendor": 420
    },
    "Verdant Pot": {
      "ask": 3956,
      "bid": 460,
      "vendor": 300
    },
    "Verdant Shears": {
      "ask": 3793,
      "bid": 470,
      "vendor": 300
    },
    "Verdant Spatula": {
      "ask": 5000,
      "bid": 465,
      "vendor": 300
    },
    "Verdant Spear": {
      "ask": 4000,
      "bid": 420,
      "vendor": 360
    },
    "Verdant Sword": {
      "ask": 5000,
      "bid": 480,
      "vendor": 360
    },
    "Vision Helmet": {
      "ask": 500000,
      "bid": 320000,
      "vendor": 20000
    },
    "Vision Shield": {
      "ask": 600000,
      "bid": 100000,
      "vendor": 20000
    },
    "Werewolf Claw": {
      "ask": 6000000,
      "bid": 2500000,
      "vendor": 10000
    },
    "Werewolf Slasher": {
      "ask": -1,
      "bid": 1337,
      "vendor": 400000
    },
    "Wheat": {
      "ask": 22,
      "bid": 21,
      "vendor": 1
    },
    "Wisdom Tea": {
      "ask": 867,
      "bid": 739,
      "vendor": 30
    },
    "Yogurt": {
      "ask": 129,
      "bid": 10,
      "vendor": 5
    }
  },
  "time": 1658915102.3430154
}